Metadata-Version: 1.1
Name: pytgressbar
Version: 1.0.0
Summary: A simple Python project to generate progressbar
Home-page: https://github.com/24aitor/pytgressbar
Author: Aitor Riba Archilla
Author-email: contact@aitorriba.com
License: MIT
Keywords: print shell progress
Platform: UNKNOWN
Classifier: Development Status :: 4 - Beta
Classifier: Intended Audience :: Developers
Classifier: Topic :: Software Development :: Build Tools
Classifier: License :: OSI Approved :: MIT License
Classifier: Programming Language :: Python :: 3
Classifier: Programming Language :: Python :: 3.3
Classifier: Programming Language :: Python :: 3.4
Classifier: Programming Language :: Python :: 3.5
